nitrowebfetch_cli/__init__.py
nitrowebfetch_cli/main.py
nitrowebfetch_cli-0.1.0.dist-info/METADATA
nitrowebfetch_cli-0.1.0.dist-info/WHEEL
nitrowebfetch_cli-0.1.0.dist-info/entry_points.txt
nitrowebfetch_cli-0.1.0.dist-info/top_level.txt
nitrowebfetch_cli-0.1.0.dist-info/RECORD
