Metadata-Version: 2.4
Name: nitrowebfetch-cli
Version: 0.1.0
Summary: The developer‑friendly web content extractor with CSS selectors.
Home-page: https://github.com/Frodigo/garage/tree/main/Projects/Nitrowebfetch
Author: Marcin Kwiatkowski
Author-email: marcin@frodigo.com
Classifier: Programming Language :: Python :: 3
Classifier: Operating System :: OS Independent
Requires-Python: >=3.8
Requires-Dist: playwright>=1.55.0
Requires-Dist: html2text>=2025.4.15
